{
    "data": [
        {
            "category": "music",
            "title": "Alice Deejay - Better Off Alone (Official Video)",
            "duration": "PT2M56S",
            "thumbnail": "https://i.ytimg.com/vi/Lgs9QUtWc3M/mqdefault.jpg",
            "videoUrl": "https://www.youtube.com/watch?v=Lgs9QUtWc3M"
        },
        {
            "category": "music",
            "title": "Harvest Moon MM - Winter Theme",
            "duration": "PT4M16S",
            "thumbnail": "https://i.ytimg.com/vi/jvKlzYeW2SA/mqdefault.jpg",
            "videoUrl": "https://www.youtube.com/watch?v=jvKlzYeW2SA"
        },
        {
            "category": "music",
            "title": "Tinnitus (돌멩이가 되고 싶어)",
            "duration": "PT2M38S",
            "thumbnail": "https://i.ytimg.com/vi/SSzegrjvxX4/mqdefault.jpg",
            "videoUrl": "https://www.youtube.com/watch?v=SSzegrjvxX4"
        },
        {
            "category": "music",
            "title": "B.I (비아이) 'BTBT' (Feat. DeVita) Official MV (Story Ver.)",
            "duration": "PT3M26S",
            "thumbnail": "https://i.ytimg.com/vi/ygJgQAYZVi0/mqdefault.jpg",
            "videoUrl": "https://www.youtube.com/watch?v=ygJgQAYZVi0"
        },
        {
            "category": "music",
            "title": "King Sis  - Big Moody (Smai Tawi)",
            "duration": "PT3M16S",
            "thumbnail": "https://i.ytimg.com/vi/CYdkHMJIGek/mqdefault.jpg",
            "videoUrl": "https://www.youtube.com/watch?v=CYdkHMJIGek"
        },
        {
            "category": "music",
            "title": "Crazy Town - Butterfly (Official Video)",
            "duration": "PT3M34S",
            "thumbnail": "https://i.ytimg.com/vi/6FEDrU85FLE/mqdefault.jpg",
            "videoUrl": "https://www.youtube.com/watch?v=6FEDrU85FLE"
        }
    ]
}